richardsplot.py
richardsplot-1.1.dist-info/DESCRIPTION.rst
richardsplot-1.1.dist-info/METADATA
richardsplot-1.1.dist-info/RECORD
richardsplot-1.1.dist-info/WHEEL
richardsplot-1.1.dist-info/metadata.json
richardsplot-1.1.dist-info/top_level.txt
