Metadata-Version: 2.0
Name: richardsplot
Version: 1.1
Summary: Matplotlib plotting standards for Gordon Richards' group
Home-page: https://github.com/gtrichards/richardsplot
Author: Gordon T. Richards
Author-email: gtr@physics.drexel.edu
License: MIT
Download-URL: https://github.com/gtrichards/richardsplot/archive/1.0.tar.gz
Keywords: richards matplotlib
Platform: UNKNOWN
Classifier: Development Status :: 5 - Production/Stable
Classifier: License :: OSI Approved :: MIT License
Classifier: Programming Language :: Python :: 2
Classifier: Programming Language :: Python :: 3
Requires-Dist: matplotlib (>=1.5.1)
Requires-Dist: palettable (>=3.0.0)
